elementsize/__init__.py
elementsize-0.1.dist-info/LICENCE.txt
elementsize-0.1.dist-info/METADATA
elementsize-0.1.dist-info/WHEEL
elementsize-0.1.dist-info/top_level.txt
elementsize-0.1.dist-info/RECORD
